setup.py
verparser.py
verparser.egg-info/PKG-INFO
verparser.egg-info/SOURCES.txt
verparser.egg-info/dependency_links.txt
verparser.egg-info/top_level.txt