Metadata-Version: 1.0
Name: verparser
Version: 0.2
Summary: Simple module for parsing version strings.
Home-page: UNKNOWN
Author: Roman Zhiharevich
Author-email: rzhiharevich@gmail.com
License: BSD 3-Clause
Keywords: version versioning simple strings
Platform: UNKNOWN
